{
  "files": {
    "src/App.tsx": "import React from 'react';\nimport { BrowserRouter as Router } from 'react-router-dom';\nimport AppRoutes from './routes/AppRoutes';\nimport { ShowProvider } from './context/ShowContext';\n\nconst App = () => {\n  return (\n    <ShowProvider>\n      <Router>\n        <div className=\"min-h-screen bg-gray-950 text-white\">\n          <AppRoutes />\n        </div>\n      </Router>\n    </ShowProvider>\n  );\n};\n\nexport default App;\n",
    "src/routes/AppRoutes.tsx": "import React from 'react';\nimport { Routes, Route } from 'react-router-dom';\nimport HomePage from '../pages/HomePage';\nimport ShowPage from '../pages/ShowPage';\nimport NotFoundPage from '../pages/NotFoundPage';\n\nconst AppRoutes = () => {\n  return (\n    <Routes>\n      <Route path=\"/\" element={<HomePage />} />\n      <Route path=\"/show/:showId\" element={<ShowPage />} />\n      <Route path=\"*\" element={<NotFoundPage />} />\n    </Routes>\n  );\n};\n\nexport default AppRoutes;\n",
    "src/pages/HomePage.tsx": "import React from 'react';\nimport Navbar from '../components/Navbar';\nimport Footer from '../components/Footer';\nimport ShowCard from '../components/ShowCard';\nimport useFetchShows from '../hooks/useFetchShows';\n\nconst HomePage = () => {\n  const { shows, loading, error } = useFetchShows();\n\n  return (\n    <div>\n      <Navbar />\n      <main className=\"max-w-6xl mx-auto px-4 py-6\">\n        <h1 className=\"text-3xl font-bold mb-4\">Trending</h1>\n        {loading && <p>Loading...</p>}\n        {error && <p>Error loading shows.</p>}\n        <div className=\"grid grid-cols-1 sm:grid-cols-2 lg:grid-cols-3 gap-4\">\n          {shows.map(show => (\n            <ShowCard key={show.id} show={show} />\n          ))}\n        </div>\n      </main>\n      <Footer />\n    </div>\n  );\n};\n\nexport default HomePage;\n",
    "src/pages/ShowPage.tsx": "import React from 'react';\nimport { useParams } from 'react-router-dom';\nimport Navbar from '../components/Navbar';\nimport Footer from '../components/Footer';\nimport LoadingSpinner from '../components/LoadingSpinner';\nimport useFetchShows from '../hooks/useFetchShows';\n\nconst ShowPage = () => {\n  const { showId } = useParams();\n  const { shows, loading, error } = useFetchShows();\n  const show = shows.find(s => s.id === showId);\n\n  return (\n    <div>\n      <Navbar />\n      <main className=\"max-w-6xl mx-auto px-4 py-6\">\n        {loading && <LoadingSpinner />}\n        {error && <p>Error loading show details.</p>}\n        {show ? (\n          <div>\n            <h1 className=\"text-3xl font-bold mb-4\">{show.title}</h1>\n            <p>{show.description}</p>\n            {/* Video player and recommendations would go here */}\n          </div>\n        ) : (\n          <p>Show not found.</p>\n        )}\n      </main>\n      <Footer />\n    </div>\n  );\n};\n\nexport default ShowPage;\n",
    "src/pages/NotFoundPage.tsx": "import React from 'react';\nimport Navbar from '../components/Navbar';\nimport Footer from '../components/Footer';\n\nconst NotFoundPage = () => {\n  return (\n    <div>\n      <Navbar />\n      <main className=\"max-w-6xl mx-auto px-4 py-6 text-center\">\n        <h1 className=\"text-4xl font-bold mb-4\">404</h1>\n        <p className=\"text-lg mb-4\">Page not found.</p>\n        <a href=\"/\" className=\"px-4 py-2 rounded-lg bg-blue-600 text-white hover:bg-blue-500 transition\">Go to Home</a>\n      </main>\n      <Footer />\n    </div>\n  );\n};\n\nexport default NotFoundPage;\n"
  }
}